<?xml version="1.0" encoding="UTF-8"?>
<archetype-descriptor
        xsi:schemaLocation="http://maven.apache.org/plugins/maven-archetype-plugin/archetype-descriptor/1.0.0 http://maven.apache.org/xsd/archetype-descriptor-1.0.0.xsd"
        name="org.wso2.carbon.authenticator.connectors.email"
        xmlns="http://maven.apache.org/plugins/maven-archetype-plugin/archetype-descriptor/1.0.0"
        xmlns:xsi="http://www.w3.org/2001/XMLSchema-instance">

    <fileSets>
        <fileSet filtered="true" encoding="UTF-8">
            <directory>src/main/openl</directory>
            <includes>
                <include>*.xml</include>
            </includes>
        </fileSet>
        <fileSet encoding="UTF-8">
            <directory>src/main/openl/rules</directory>
            <includes>
                <include>*.xlsx</include>
            </includes>
        </fileSet>
        <fileSet encoding="UTF-8">
            <directory>src/test/openl</directory>
            <includes>
                <include>**/*.*</include>
            </includes>
        </fileSet>
        <fileSet filtered="true" encoding="UTF-8">
            <directory></directory>
            <includes>
                <include>ReadMe.txt</include>
            </includes>
        </fileSet>
    </fileSets>

</archetype-descriptor>