<?xml version="1.0" encoding="UTF-8"?>
<beans xmlns="http://www.springframework.org/schema/beans" xmlns:xsi="http://www.w3.org/2001/XMLSchema-instance"
  xsi:schemaLocation="http://www.springframework.org/schema/beans http://www.springframework.org/schema/beans/spring-beans-2.5.xsd"
  default-autowire="no">

  <bean id="eclipseBasedStrategy" class="org.openl.rules.project.resolving.EclipseBasedResolvingStrategy"/>
  <bean id="fileTreeAdaptor" class="org.openl.util.tree.FileTreeIterator$FileTreeAdaptor"/>
  
  <bean id="projectResolver" class="org.openl.rules.project.resolving.RulesProjectResolver">
    <property name="resolvingStrategies">
      <list>
        <ref bean="eclipseBasedStrategy"/>
      </list>
    </property>
    <property name="workspace" value=".."/>
    <property name="projectsTreeAdaptor" ref="fileTreeAdaptor"/>
  </bean>
</beans>
